lumera/__init__.py
lumera/google.py
lumera/sdk.py
lumera-0.4.14.dist-info/METADATA
lumera-0.4.14.dist-info/WHEEL
lumera-0.4.14.dist-info/top_level.txt
lumera-0.4.14.dist-info/RECORD
