Metadata-Version: 2.4
Name: lumera
Version: 0.4.14
Summary: Lumera Agent SDK for API interaction and dynamic UI generation.
Requires-Python: >=3.8
Requires-Dist: requests
Requires-Dist: python-dotenv
Requires-Dist: google-api-python-client==2.173.0
Provides-Extra: dev
Requires-Dist: ruff; extra == "dev"
Requires-Dist: pytest; extra == "dev"
Provides-Extra: full
Requires-Dist: airtable-python-wrapper==0.15.3; extra == "full"
Requires-Dist: boto3==1.39.3; extra == "full"
Requires-Dist: google-api-python-client==2.173.0; extra == "full"
Requires-Dist: gspread==6.2.1; extra == "full"
Requires-Dist: hubspot-api-client==12.0.0; extra == "full"
Requires-Dist: ipykernel; extra == "full"
Requires-Dist: jupyter-client; extra == "full"
Requires-Dist: matplotlib==3.10.3; extra == "full"
Requires-Dist: notion-client==2.4.0; extra == "full"
Requires-Dist: numpy==2.3.0; extra == "full"
Requires-Dist: openai; extra == "full"
Requires-Dist: openai-agents; extra == "full"
Requires-Dist: openpyxl==3.1.5; extra == "full"
Requires-Dist: pandas==2.3.0; extra == "full"
Requires-Dist: pdfplumber; extra == "full"
Requires-Dist: pydantic==2.11.7; extra == "full"
Requires-Dist: PyGithub==2.6.1; extra == "full"
Requires-Dist: python-dotenv==1.1.0; extra == "full"
Requires-Dist: pyzmq; extra == "full"
Requires-Dist: simple-salesforce==1.12.6; extra == "full"
Requires-Dist: slack_sdk==3.35.0; extra == "full"
Requires-Dist: tabulate; extra == "full"
Requires-Dist: xlsxwriter==3.2.5; extra == "full"
Requires-Dist: requests==2.32.4; extra == "full"
